yhttp/ext/dbmanager/__init__.py
yhttp/ext/dbmanager/cli.py
yhttp/ext/dbmanager/dbmanager.py
yhttp/ext/dbmanager/install.py
yhttp/ext/dbmanager/uri.py
yhttp_dbmanager-6.0.2.dist-info/licenses/LICENSE
yhttp_dbmanager-6.0.2.dist-info/METADATA
yhttp_dbmanager-6.0.2.dist-info/WHEEL
yhttp_dbmanager-6.0.2.dist-info/top_level.txt
yhttp_dbmanager-6.0.2.dist-info/RECORD
